{
    "stringKeys": [],
    "stringValues": [],
    "floatKeys": [],
    "floatValues": [],
    "intKeys": [],
    "intValues": [],
    "intExample": 5,
    "strExample": "Hello!",
    "boolExample": [
        false,
        false,
        false,
        false
    ],
    "idSave": 1288,
    "soundEnabled": true,
    "musicEnabled": true,
    "aiLevel": 0,
    "customPlayerName": "",
    "selectedAvatarIndex": 2,
    "unlockedAvatars": [
        true,
        false,
        true,
        false,
        false,
        false,
        false,
        false
    ],
    "totalScore": -21,
    "recordScore": 14,
    "animationSpeed": 2.0,
    "currentQuestId": 0,
    "currentQuestStep": 0,
    "questHoldCounter": 0,
    "tutorialCompleted": false
}